xlsx2dfs/__init__.py
xlsx2dfs-0.1.0.post6.dist-info/WHEEL
xlsx2dfs-0.1.0.post6.dist-info/METADATA
xlsx2dfs-0.1.0.post6.dist-info/RECORD
