Metadata-Version: 2.1
Name: xlsx2dfs
Version: 0.1.0.post6
Summary: Read and write list of `pandas.DataFrame`s of tabular data from/to excel file.
Home-page: https://bitbucket.org/gwangjinkim/xlsx2dfs/src
License: MIT
Keywords: Excel,Pandas,data frame,I/O
Author: Gwang-Jin Kim
Author-email: gwang.jin.kim.phd@gmail.com
Maintainer: Gwang-Jin Kim
Maintainer-email: gwang.jin.kim.phd@gmail.com
Requires-Python: >=3.7.1,<4.0.0
Classifier: License :: OSI Approved :: MIT License
Classifier: Programming Language :: Python :: 3
Classifier: Programming Language :: Python :: 3.8
Classifier: Programming Language :: Python :: 3.9
Requires-Dist: pandas (>=1.2.4,<2.0.0)
Project-URL: Repository, https://bitbucket.org/gwangjinkim/xlsx2dfs/src
